wematics/__init__.py
wematics/skycamera.py
wematics-0.3.0.dist-info/METADATA
wematics-0.3.0.dist-info/WHEEL
wematics-0.3.0.dist-info/top_level.txt
wematics-0.3.0.dist-info/RECORD
