Metadata-Version: 2.1
Name: wematics
Version: 0.3.0
Summary: A client library for Wematics sky cameras
Author: Wematics
Author-email: info@wematics.com
Classifier: Programming Language :: Python :: 3
Classifier: License :: OSI Approved :: MIT License
Classifier: Operating System :: OS Independent
Requires-Python: >=3.6
Requires-Dist: requests
Requires-Dist: tqdm
Requires-Dist: timezonefinder
